Metadata-Version: 2.1
Name: pytest-pumpkin-spice
Version: 0.1.0
Summary: A pytest plugin that makes your test reporting pumpkin-spiced
Home-page: https://github.com/hackebrot/pytest-pumpkin-spice
Author: Josh Grant
Author-email: joshua.m.grant@gmail.com
Maintainer: Josh Grant
Maintainer-email: joshua.m.grant@gmail.com
License: MIT
Keywords: pytest,pumpkin spice,autumn
Platform: UNKNOWN
Classifier: Development Status :: 4 - Beta
Classifier: Framework :: Pytest
Classifier: Intended Audience :: Developers
Classifier: Topic :: Software Development :: Testing
Classifier: Programming Language :: Python
Classifier: Programming Language :: Python :: 3
Classifier: Programming Language :: Python :: 3.6
Classifier: Programming Language :: Python :: 3.7
Classifier: Programming Language :: Python :: 3.8
Classifier: Programming Language :: Python :: 3.9
Classifier: Programming Language :: Python :: Implementation :: CPython
Classifier: Operating System :: OS Independent
Classifier: License :: OSI Approved :: MIT License
Requires-Python: >=3.6
License-File: LICENSE
